pytest_executable/__init__.py
pytest_executable/file_tools.py
pytest_executable/plugin.py
pytest_executable/report-db-schema.yaml
pytest_executable/report.py
pytest_executable/script_runner.py
pytest_executable/settings.py
pytest_executable/test-settings-schema.yaml
pytest_executable/test-settings.yaml
pytest_executable/test_executable.py
pytest_executable/yaml_helper.py
pytest_executable-0.5.6.dist-info/LICENSE.txt
pytest_executable-0.5.6.dist-info/METADATA
pytest_executable-0.5.6.dist-info/WHEEL
pytest_executable-0.5.6.dist-info/entry_points.txt
pytest_executable-0.5.6.dist-info/top_level.txt
pytest_executable-0.5.6.dist-info/RECORD
