Metadata-Version: 2.1
Name: pytest-executable
Version: 0.5.6
Summary: pytest plugin for testing executables
Author: Antoine Dechaume
License: Apache Software License 2.0
Project-URL: Homepage, https://www.github.com/CS-SI/pytest-executable
Classifier: Environment :: Console
Classifier: Framework :: Pytest
Classifier: License :: OSI Approved :: Apache Software License
Classifier: Operating System :: MacOS
Classifier: Operating System :: POSIX :: Linux
Classifier: Programming Language :: Python
Classifier: Programming Language :: Python :: 3
Classifier: Programming Language :: Python :: 3 :: Only
Classifier: Programming Language :: Python :: 3.8
Classifier: Programming Language :: Python :: 3.9
Classifier: Programming Language :: Python :: 3.10
Classifier: Programming Language :: Python :: 3.11
Classifier: Programming Language :: Python :: 3.12
Classifier: Topic :: Software Development :: Libraries
Classifier: Topic :: Software Development :: Testing
Classifier: Topic :: Utilities
Requires-Python: <3.13,>=3.8
License-File: LICENSE.txt
Requires-Dist: delta <0.5,>=0.4
Requires-Dist: jinja2 <3.2,>=2.7
Requires-Dist: jsonschema <5,>=2
Requires-Dist: pytest <8,>=5
Requires-Dist: pyyaml <6.1,>=3
Provides-Extra: test
Requires-Dist: covdefaults ; extra == 'test'
Requires-Dist: pytest-cov ; extra == 'test'
